README.md
dragon_form_validator.py
setup.py
dragon_form_validator.egg-info/PKG-INFO
dragon_form_validator.egg-info/SOURCES.txt
dragon_form_validator.egg-info/dependency_links.txt
dragon_form_validator.egg-info/top_level.txt